setup.py
website_status/__init__.py
website_status.egg-info/PKG-INFO
website_status.egg-info/SOURCES.txt
website_status.egg-info/dependency_links.txt
website_status.egg-info/not-zip-safe
website_status.egg-info/requires.txt
website_status.egg-info/top_level.txt