Metadata-Version: 1.0
Name: website-status
Version: 0.0.3
Summary: Check whether a website is up or down
Home-page: http://github.com/sahildua2305/website_status
Author: Sahil Dua
Author-email: sahildua2305@gmail.com
License: MIT
Keywords: website status website down website up
Platform: UNKNOWN
